quickbase_client/__init__.py
quickbase_client/__version__.py
quickbase_client/client/__init__.py
quickbase_client/client/api.py
quickbase_client/client/legacy_client.py
quickbase_client/client/pager.py
quickbase_client/client/request_factory.py
quickbase_client/client/table_client.py
quickbase_client/orm/__init__.py
quickbase_client/orm/app.py
quickbase_client/orm/field.py
quickbase_client/orm/report.py
quickbase_client/orm/serialize.py
quickbase_client/orm/table.py
quickbase_client/query/__init__.py
quickbase_client/query/ast.py
quickbase_client/query/query_base.py
quickbase_client/query/query_utils.py
quickbase_client/tools/__init__.py
quickbase_client/tools/log_handler.py
quickbase_client/tools/model_generate.py
quickbase_client/tools/qbc.py
quickbase_client/tools/script.py
quickbase_client/tools/script_loader.py
quickbase_client/utils/__init__.py
quickbase_client/utils/_stringcase.py
quickbase_client/utils/pywriting_utils.py
quickbase_client/utils/string_utils.py
quickbase_client-0.9.0.dist-info/LICENSE.md
quickbase_client-0.9.0.dist-info/METADATA
quickbase_client-0.9.0.dist-info/WHEEL
quickbase_client-0.9.0.dist-info/entry_points.txt
quickbase_client-0.9.0.dist-info/RECORD
