Metadata-Version: 2.3
Name: quickbase-client
Version: 0.9.0
Summary: A Quickbase Python API Client Generator
License: LICENSE.md
Keywords: quickbase,client,quickbase-api,orm,generator
Author: Tim Kutcher
Author-email: tim@tkutcher.com
Maintainer: Tim Kutcher
Maintainer-email: tim@tkutcher.com
Requires-Python: >=3.9,<4.0
Classifier: Development Status :: 4 - Beta
Classifier: Intended Audience :: Developers
Classifier: License :: OSI Approved :: MIT License
Classifier: License :: Other/Proprietary License
Classifier: Operating System :: OS Independent
Classifier: Programming Language :: Python :: 3
Classifier: Programming Language :: Python :: 3.9
Classifier: Programming Language :: Python :: 3.10
Classifier: Programming Language :: Python :: 3.11
Classifier: Programming Language :: Python :: 3.12
Classifier: Programming Language :: Python :: 3.13
Classifier: Programming Language :: Python :: 3.8
Requires-Dist: attrs (>=23.2.0,<24.0.0)
Requires-Dist: requests (>=2.31.0,<3.0.0)
Project-URL: Bug Tracker, https://github.com/tkutcher/quickbase-client/issues
Project-URL: Documentation, https://quickbase-client.readthedocs.io/en/latest/?badge=latest
Project-URL: Homepage, https://github.com/tkutcher/quickbase-client
Project-URL: Repository, https://github.com/tkutcher/quickbase-client
